{"trial_id": "02", "hyperparameters": {"space": [{"class_name": "Int", "config": {"name": "conv_1", "default": null, "conditions": [], "min_value": 32, "max_value": 128, "step": 32, "sampling": "linear"}}, {"class_name": "Int", "config": {"name": "units_2", "default": null, "conditions": [], "min_value": 3, "max_value": 7, "step": 1, "sampling": "linear"}}, {"class_name": "Int", "config": {"name": "conv_2", "default": null, "conditions": [], "min_value": 16, "max_value": 64, "step": 16, "sampling": "linear"}}, {"class_name": "Int", "config": {"name": "units_3", "default": null, "conditions": [], "min_value": 7, "max_value": 11, "step": 1, "sampling": "linear"}}], "values": {"conv_1": 32, "units_2": 4, "conv_2": 32, "units_3": 7}}, "metrics": {"metrics": {}}, "score": null, "best_step": 0, "status": "RUNNING", "message": null}